fourcats_utils/__init__.py
fourcats_utils/configfile.py
fourcats_utils/logger.py
fourcats_utils/registry.py
fourcats_utils/requester.py
fourcats_utils-0.0.4.dist-info/LICENSE
fourcats_utils-0.0.4.dist-info/METADATA
fourcats_utils-0.0.4.dist-info/WHEEL
fourcats_utils-0.0.4.dist-info/top_level.txt
fourcats_utils-0.0.4.dist-info/RECORD
