Metadata-Version: 2.1
Name: fourcats-utils
Version: 0.0.4
Summary: A common Python toolkit package based on personal habits.
Home-page: https://github.com/FourCats-Py/FourCats-Utils
Download-URL: https://github.com/FourCats-Py/FourCats-Utils/archive/0.0.4.tar.gz
Author: ShiWeiDong
Author-email: shiweidong1993@gmail.com
Keywords: fourcats,utils
Requires-Python: >=3.8
License-File: LICENSE
Requires-Dist: loguru (>=0.6.0)
Requires-Dist: mergedict (>=1.0.0)
Requires-Dist: PyYAML (>=6.0)
Requires-Dist: urllib3 (>=1.26.11)
